pyg3a/__init__.py
pyg3a/__main__.py
pyg3a/block.py
pyg3a/errors.py
pyg3a/functions.py
pyg3a/logging.py
pyg3a/node.py
pyg3a/py.typed
pyg3a/py_consts.py
pyg3a/pyg3a.py
pyg3a/scope.py
pyg3a/selected.bmp
pyg3a/type_registry.py
pyg3a/type_utils.py
pyg3a/unselected.bmp
pyg3a/include/list.hpp
pyg3a/include/str.hpp
pyg3a/modules/__init__.py
pyg3a/modules/functions.py
pyg3a/modules/modules.py
pyg3a/packages/casioplot.py
pyg3a/packages/fxcg.py
pyg3a/packages/stdc.py
pyg3a/packages/stdpy.py
pyg3a/types/__init__.py
pyg3a/types/callable.py
pyg3a/types/enum.py
pyg3a/types/generics.py
pyg3a/types/list.py
pyg3a/types/misc.py
pyg3a/types/numbers.py
pyg3a/types/object.py
pyg3a/types/sequence.py
pyg3a/types/string.py
pyg3a/types/tuples.py
pyg3a/types/type_alias.py
pyg3a-0.2.5.dist-info/LICENSE
pyg3a-0.2.5.dist-info/METADATA
pyg3a-0.2.5.dist-info/WHEEL
pyg3a-0.2.5.dist-info/entry_points.txt
pyg3a-0.2.5.dist-info/top_level.txt
pyg3a-0.2.5.dist-info/RECORD
